wordgradient/__init__.py
wordgradient/__main__.py
wordgradient/_csv_reader.py
wordgradient/command_line.py
wordgradient/wordlist/__init__.py
wordgradient/wordlist/unigram_freq.csv
wordgradient-0.5.dist-info/LICENSE
wordgradient-0.5.dist-info/METADATA
wordgradient-0.5.dist-info/WHEEL
wordgradient-0.5.dist-info/entry_points.txt
wordgradient-0.5.dist-info/top_level.txt
wordgradient-0.5.dist-info/zip-safe
wordgradient-0.5.dist-info/RECORD
